{
  "data": {
    "repository": {
      "pullRequest": {
        "additions": 74,
        "assignees": {
          "nodes": []
        },
        "author": {
          "login": "Parcly-Taxel"
        },
        "autoMergeRequest": null,
        "baseRefName": "master",
        "body": "`cliqueFree_of_replaceVertex_cliqueFree` is still quite long.\r\n\r\n---\r\n<!-- The text above the `---` will become the commit message when your\r\nPR is merged. Please leave a blank newline before the `---`, otherwise\r\nGitHub will format the text above it as a title.\r\n\r\nTo indicate co-authors, include lines at the bottom of the commit message\r\n(that is, before the `---`) using the following format:\r\n\r\nCo-authored-by: Author Name <author@email.com>\r\n\r\nAny other comments you want to keep out of the PR commit should go\r\nbelow the `---`, and placed outside this HTML comment, or else they\r\nwill be invisible to reviewers.\r\n\r\nIf this PR depends on other PRs, please list them below this comment,\r\nusing the following format:\r\n- [ ] depends on: #abc [optional extra text]\r\n- [ ] depends on: #xyz [optional extra text]\r\n-->\r\n\r\n[![Open in Gitpod](https://gitpod.io/button/open-in-gitpod.svg)](https://gitpod.io/from-referrer/)\r\n",
        "changedFiles": 2,
        "closed": true,
        "closedAt": "2023-10-14T07:39:43Z",
        "comments": {
          "nodes": [
            {
              "id": "IC_kwDOFcwZ1c5n3noA",
              "body": ":v: Parcly-Taxel can now approve this pull request. To approve and merge a pull request, simply reply with `bors r+`. More detailed instructions are available [here](https://bors.tech/documentation/getting-started/#reviewing-pull-requests).",
              "createdAt": "2023-10-02T08:51:04Z",
              "author": {
                "login": "bors"
              }
            },
            {
              "id": "IC_kwDOFcwZ1c5pEC8P",
              "body": "bors merge",
              "createdAt": "2023-10-14T06:47:35Z",
              "author": {
                "login": "Parcly-Taxel"
              }
            },
            {
              "id": "IC_kwDOFcwZ1c5pEDK5",
              "body": "Canceled.",
              "createdAt": "2023-10-14T06:52:10Z",
              "author": {
                "login": "bors"
              }
            },
            {
              "id": "IC_kwDOFcwZ1c5pED3L",
              "body": "bors merge",
              "createdAt": "2023-10-14T07:05:23Z",
              "author": {
                "login": "Parcly-Taxel"
              }
            },
            {
              "id": "IC_kwDOFcwZ1c5pELSa",
              "body": "Pull request successfully merged into master.\n\n  Build succeeded!\n\n  The publicly hosted instance of bors-ng is deprecated and will go away soon.\n\n  If you want to self-host your own instance, [instructions are here][instructions].\n  For more help, visit [the forum].\n\n  If you want to switch to GitHub's built-in merge queue, visit [their help page][gh].\n\n  [instructions]: https://github.com/bors-ng/bors-ng#how-to-set-up-your-own-real-instance\n  [the forum]: https://forum.bors.tech\n  [gh]: https://docs.github.com/en/repositories/configuring-branches-and-merges-in-your-repository/configuring-pull-request-merges/managing-a-merge-queue\n\n\n\n  * [Build](https://github.com/leanprover-community/mathlib4/actions/runs/6516233908/job/17699534268)\n  * [Check all files imported](https://github.com/leanprover-community/mathlib4/actions/runs/6516233908/job/17699534339)\n  * [Lint style](https://github.com/leanprover-community/mathlib4/actions/runs/6516233908/job/17699534496)",
              "createdAt": "2023-10-14T07:39:42Z",
              "author": {
                "login": "bors"
              }
            }
          ]
        },
        "commits": {
          "nodes": [
            {
              "commit": {
                "oid": "26031eec02f865a222dae2126e4b7b304b528a4c",
                "additions": 119,
                "deletions": 0,
                "committedDate": "2023-08-27T08:15:32Z",
                "author": {
                  "name": "Parcly Taxel",
                  "email": "reddeloostw@gmail.com"
                },
                "statusCheckRollup": null
              }
            },
            {
              "commit": {
                "oid": "54fa1b4ee5d5c65be287778c0bf75a9d3598af94",
                "additions": 1947,
                "deletions": 392,
                "committedDate": "2023-08-29T02:40:15Z",
                "author": {
                  "name": "Parcly Taxel",
                  "email": "reddeloostw@gmail.com"
                },
                "statusCheckRollup": null
              }
            },
            {
              "commit": {
                "oid": "cee96c0e236b4bf40844012894e14c3159b35b7b",
                "additions": 28,
                "deletions": 87,
                "committedDate": "2023-08-29T08:28:15Z",
                "author": {
                  "name": "Parcly Taxel",
                  "email": "reddeloostw@gmail.com"
                },
                "statusCheckRollup": null
              }
            },
            {
              "commit": {
                "oid": "78a277cf8c931568a90c369e9086f375367f0321",
                "additions": 3,
                "deletions": 4,
                "committedDate": "2023-08-29T08:39:19Z",
                "author": {
                  "name": "Parcly Taxel",
                  "email": "reddeloostw@gmail.com"
                },
                "statusCheckRollup": null
              }
            },
            {
              "commit": {
                "oid": "cae2c37f1cd72ed23f5291ca970e033e8b60c4f6",
                "additions": 26,
                "deletions": 3,
                "committedDate": "2023-10-14T06:30:32Z",
                "author": {
                  "name": "Jeremy Tan Jie Rui",
                  "email": "reddeloostw@gmail.com"
                },
                "statusCheckRollup": null
              }
            },
            {
              "commit": {
                "oid": "5c27edfe8ae99b200c16b8d9bb049a57ccc5448b",
                "additions": 56637,
                "deletions": 24244,
                "committedDate": "2023-10-14T06:40:13Z",
                "author": {
                  "name": "Parcly Taxel",
                  "email": "reddeloostw@gmail.com"
                },
                "statusCheckRollup": null
              }
            },
            {
              "commit": {
                "oid": "5a767eae921bbdbeb8df0488a1fcfd4347167ebc",
                "additions": 1,
                "deletions": 1,
                "committedDate": "2023-10-14T06:42:11Z",
                "author": {
                  "name": "Parcly Taxel",
                  "email": "reddeloostw@gmail.com"
                },
                "statusCheckRollup": null
              }
            },
            {
              "commit": {
                "oid": "0c9add7a780c4aac2dbe7b6376dc44448ef5779d",
                "additions": 2,
                "deletions": 2,
                "committedDate": "2023-10-14T06:46:02Z",
                "author": {
                  "name": "Parcly Taxel",
                  "email": "reddeloostw@gmail.com"
                },
                "statusCheckRollup": null
              }
            },
            {
              "commit": {
                "oid": "e09355f8dc198cf9231458bcb5dde129a36aadbc",
                "additions": 1,
                "deletions": 5,
                "committedDate": "2023-10-14T06:52:02Z",
                "author": {
                  "name": "Parcly Taxel",
                  "email": "reddeloostw@gmail.com"
                },
                "statusCheckRollup": null
              }
            },
            {
              "commit": {
                "oid": "fb09cf6820561d51553c7ca5de6129be554265c5",
                "additions": 6,
                "deletions": 10,
                "committedDate": "2023-10-14T07:02:47Z",
                "author": {
                  "name": "Parcly Taxel",
                  "email": "reddeloostw@gmail.com"
                },
                "statusCheckRollup": null
              }
            }
          ]
        },
        "createdAt": "2023-08-27T08:16:52Z",
        "deletions": 0,
        "files": {
          "nodes": [
            {
              "path": "Mathlib/Combinatorics/SimpleGraph/Basic.lean",
              "additions": 37,
              "deletions": 0
            },
            {
              "path": "Mathlib/Combinatorics/SimpleGraph/Clique.lean",
              "additions": 37,
              "deletions": 0
            }
          ]
        },
        "headRefName": "replaceVertex",
        "headRefOid": "fb09cf6820561d51553c7ca5de6129be554265c5",
        "headRepository": {
          "name": "mathlib4",
          "owner": {
            "login": "leanprover-community"
          }
        },
        "headRepositoryOwner": {
          "login": "leanprover-community"
        },
        "id": "PR_kwDOFcwZ1c5Y3Trl",
        "isCrossRepository": false,
        "isDraft": false,
        "labels": {
          "nodes": [
            {
              "id": "LA_kwDOFcwZ1c8AAAABAt13Ow",
              "color": "bfd4f2",
              "name": "delegated"
            },
            {
              "id": "LA_kwDOFcwZ1c8AAAABViJPeA",
              "color": "33dbec",
              "name": "t-combinatorics"
            }
          ]
        },
        "latestReviews": {
          "nodes": [
            {
              "id": "PRR_kwDOFcwZ1c5ifE_y",
              "body": "Thanks!\r\n\r\nPlease apply the suggestions and then feel free to merge.\r\n\r\nbors d+",
              "state": "APPROVED",
              "author": {
                "login": "ocfnash"
              },
              "submittedAt": "2023-10-02T08:51:02Z"
            }
          ]
        },
        "maintainerCanModify": false,
        "mergeCommit": null,
        "mergeStateStatus": "UNKNOWN",
        "mergeable": "UNKNOWN",
        "mergedAt": null,
        "mergedBy": null,
        "milestone": null,
        "number": 6808,
        "potentialMergeCommit": null,
        "projectCards": {
          "nodes": []
        },
        "reactionGroups": [
          {
            "content": "THUMBS_UP",
            "users": {
              "nodes": []
            }
          },
          {
            "content": "THUMBS_DOWN",
            "users": {
              "nodes": []
            }
          },
          {
            "content": "LAUGH",
            "users": {
              "nodes": []
            }
          },
          {
            "content": "HOORAY",
            "users": {
              "nodes": []
            }
          },
          {
            "content": "CONFUSED",
            "users": {
              "nodes": []
            }
          },
          {
            "content": "HEART",
            "users": {
              "nodes": []
            }
          },
          {
            "content": "ROCKET",
            "users": {
              "nodes": []
            }
          },
          {
            "content": "EYES",
            "users": {
              "nodes": []
            }
          }
        ],
        "reviewDecision": "APPROVED",
        "reviewRequests": {
          "nodes": [
            {
              "requestedReviewer": {
                "id": "MDQ6VXNlcjQyNTI2MA==",
                "login": "eric-wieser"
              }
            }
          ]
        },
        "reviews": {
          "nodes": [
            {
              "id": "PRR_kwDOFcwZ1c5fMo62",
              "body": "",
              "state": "COMMENTED",
              "author": {
                "login": "eric-wieser"
              },
              "submittedAt": "2023-08-27T14:48:05Z"
            },
            {
              "id": "PRR_kwDOFcwZ1c5fMpAv",
              "body": "",
              "state": "COMMENTED",
              "author": {
                "login": "eric-wieser"
              },
              "submittedAt": "2023-08-27T14:50:43Z"
            },
            {
              "id": "PRR_kwDOFcwZ1c5fWy8i",
              "body": "",
              "state": "COMMENTED",
              "author": {
                "login": "Parcly-Taxel"
              },
              "submittedAt": "2023-08-29T08:30:57Z"
            },
            {
              "id": "PRR_kwDOFcwZ1c5ifE_y",
              "body": "Thanks!\r\n\r\nPlease apply the suggestions and then feel free to merge.\r\n\r\nbors d+",
              "state": "APPROVED",
              "author": {
                "login": "ocfnash"
              },
              "submittedAt": "2023-10-02T08:51:02Z"
            }
          ]
        },
        "reviewThreads": {
          "nodes": [
            {
              "comments": {
                "nodes": [
                  {
                    "id": "PRRC_kwDOFcwZ1c5N4lG5",
                    "body": "You could do\r\n```lean\r\nAdj u v :=\r\n  if u = t then\r\n    if v = t then\r\n        False\r\n    else\r\n        G.Adj s v\r\n  else\r\n    if v = t then\r\n        G.Adj u s\r\n    else\r\n        G.Adj u v\r\n```\r\nIf you're lucky the proofs follow by case-bashing, but I have no idea if this is better than your approach.",
                    "createdAt": "2023-08-27T14:48:05Z",
                    "author": {
                      "login": "eric-wieser"
                    }
                  },
                  {
                    "id": "PRRC_kwDOFcwZ1c5N4lM-",
                    "body": "Ah, that's not quite right because I didn't handle the s-t edge",
                    "createdAt": "2023-08-27T14:50:43Z",
                    "author": {
                      "login": "eric-wieser"
                    }
                  },
                  {
                    "id": "PRRC_kwDOFcwZ1c5N_M40",
                    "body": "Actually your if-else tree works once `[DecidableEq V]` is added – see `not_adj_of_replaceVertex` in the latest commit – and all proofs shorten with this change. But `cliqueFree_of_replaceVertex_cliqueFree` is still quite long.",
                    "createdAt": "2023-08-29T08:30:57Z",
                    "author": {
                      "login": "Parcly-Taxel"
                    }
                  }
                ]
              }
            },
            {
              "comments": {
                "nodes": [
                  {
                    "id": "PRRC_kwDOFcwZ1c5QA5NN",
                    "body": "I think this is slightly clearer:\r\n```suggestion\r\n                      else if w = t then G.Adj v s else G.Adj v w\r\n```",
                    "createdAt": "2023-10-02T08:30:49Z",
                    "author": {
                      "login": "ocfnash"
                    }
                  }
                ]
              }
            },
            {
              "comments": {
                "nodes": [
                  {
                    "id": "PRRC_kwDOFcwZ1c5QA9cW",
                    "body": "```suggestion\r\n/-- The graph formed by forgetting `t`'s neighbours and instead giving it those of `s`. The `s-t`\r\nedge is removed if present. -/\r\n```",
                    "createdAt": "2023-10-02T08:48:47Z",
                    "author": {
                      "login": "ocfnash"
                    }
                  }
                ]
              }
            },
            {
              "comments": {
                "nodes": [
                  {
                    "id": "PRRC_kwDOFcwZ1c5QA9oH",
                    "body": "We should characterise `replaceVertex` with some API:\r\n```suggestion\r\n\r\n/-- There is never an `s-t` edge in `G.replaceVertex s t`. -/\r\nlemma not_adj_replaceVertex_same :\r\n    ¬ (G.replaceVertex s t).Adj s t := by\r\n  simp\r\n\r\n/-- Except possibly for `t`, the neighbours of `s` in `G.replaceVertex s t` are its neighbours in\r\n`G`. -/\r\nlemma adj_replaceVertex_iff_of_ne_left {w : V} (hw : w ≠ t) :\r\n    (G.replaceVertex s t).Adj s w ↔ G.Adj s w := by\r\n  simp [hw]\r\n\r\n/-- Except possibly for itself, the neighbours of `t` in `G.replaceVertex s t` are the neighbours of\r\n`s` in `G`. -/\r\nlemma adj_replaceVertex_iff_of_ne_right {w : V} (hw : w ≠ t) :\r\n    (G.replaceVertex s t).Adj t w ↔ G.Adj s w := by\r\n  simp [hw]\r\n\r\n/-- Adjacency in `G.replaceVertex s t` which does not involve `s` or `t` is the same as that of\r\n`G`. -/\r\nlemma adj_replaceVertex_iff_of_ne {v w : V} (hv : v ≠ t) (hw : w ≠ t) (hv' : v ≠ s) (hw' : w ≠ s) :\r\n    (G.replaceVertex s t).Adj v w ↔ G.Adj v w := by\r\n  simp [hv, hw, hv', hw']\r\n\r\n```",
                    "createdAt": "2023-10-02T08:49:31Z",
                    "author": {
                      "login": "ocfnash"
                    }
                  }
                ]
              }
            }
          ]
        },
        "closingIssuesReferences": {
          "nodes": []
        },
        "participants": {
          "nodes": [
            {
              "id": "MDQ6VXNlcjU0MTc1NDYz",
              "login": "Parcly-Taxel"
            },
            {
              "id": "MDQ6VXNlcjQyNTI2MA==",
              "login": "eric-wieser"
            },
            {
              "id": "MDQ6VXNlcjc3MzQzNjQ=",
              "login": "ocfnash"
            },
            {
              "id": "U_kgDOB75MNQ",
              "login": "leanprover-community-mathlib4-bot"
            }
          ]
        },
        "state": "CLOSED",
        "statusCheckRollup": null,
        "title": "[Merged by Bors] - feat: vertex replacement",
        "updatedAt": "2023-10-14T07:39:47Z",
        "url": "https://github.com/leanprover-community/mathlib4/pull/6808",
        "timelineItems": {
          "nodes": [
            {
              "__typename": "PullRequestCommit",
              "commit": {
                "oid": "26031eec02f865a222dae2126e4b7b304b528a4c"
              }
            },
            {
              "__typename": "LabeledEvent",
              "id": "LE_lADOFcwZ1c5vXZ0ozwAAAAJgDIcf",
              "createdAt": "2023-08-27T08:16:52Z",
              "label": {
                "id": "LA_kwDOFcwZ1c7ECuhA",
                "name": "awaiting-review"
              }
            },
            {
              "__typename": "LabeledEvent",
              "id": "LE_lADOFcwZ1c5vXZ0ozwAAAAJgDIcg",
              "createdAt": "2023-08-27T08:16:52Z",
              "label": {
                "id": "LA_kwDOFcwZ1c8AAAABMtntmA",
                "name": "new-feature"
              }
            },
            {
              "__typename": "LabeledEvent",
              "id": "LE_lADOFcwZ1c5vXZ0ozwAAAAJgDIci",
              "createdAt": "2023-08-27T08:16:52Z",
              "label": {
                "id": "LA_kwDOFcwZ1c8AAAABViJPeA",
                "name": "t-combinatorics"
              }
            },
            {
              "__typename": "ReviewRequestedEvent",
              "id": "RRE_lADOFcwZ1c5vXZ0ozwAAAAJgDIwx",
              "createdAt": "2023-08-27T08:17:34Z",
              "requestedReviewer": {
                "id": "MDQ6VXNlcjQyNTI2MA==",
                "login": "eric-wieser"
              }
            },
            {
              "__typename": "PullRequestReview",
              "id": "PRR_kwDOFcwZ1c5fMo62",
              "createdAt": "2023-08-27T14:48:05Z",
              "body": "",
              "author": {
                "login": "eric-wieser"
              }
            },
            {
              "__typename": "PullRequestCommit",
              "commit": {
                "oid": "54fa1b4ee5d5c65be287778c0bf75a9d3598af94"
              }
            },
            {
              "__typename": "PullRequestCommit",
              "commit": {
                "oid": "cee96c0e236b4bf40844012894e14c3159b35b7b"
              }
            },
            {
              "__typename": "PullRequestCommit",
              "commit": {
                "oid": "78a277cf8c931568a90c369e9086f375367f0321"
              }
            },
            {
              "__typename": "ReviewRequestedEvent",
              "id": "RRE_lADOFcwZ1c5vXZ0ozwAAAAJjGCwQ",
              "createdAt": "2023-09-01T03:11:10Z",
              "requestedReviewer": {
                "id": "MDQ6VXNlcjQyNTI2MA==",
                "login": "eric-wieser"
              }
            },
            {
              "__typename": "BaseRefChangedEvent"
            },
            {
              "__typename": "BaseRefChangedEvent"
            },
            {
              "__typename": "PullRequestReview",
              "id": "PRR_kwDOFcwZ1c5ifE_y",
              "createdAt": "2023-10-02T08:30:49Z",
              "body": "Thanks!\r\n\r\nPlease apply the suggestions and then feel free to merge.\r\n\r\nbors d+",
              "author": {
                "login": "ocfnash"
              }
            },
            {
              "__typename": "IssueComment",
              "id": "IC_kwDOFcwZ1c5n3noA",
              "createdAt": "2023-10-02T08:51:04Z",
              "body": ":v: Parcly-Taxel can now approve this pull request. To approve and merge a pull request, simply reply with `bors r+`. More detailed instructions are available [here](https://bors.tech/documentation/getting-started/#reviewing-pull-requests).",
              "author": {
                "login": "bors"
              }
            },
            {
              "__typename": "LabeledEvent",
              "id": "LE_lADOFcwZ1c5vXZ0ozwAAAAJzQLR9",
              "createdAt": "2023-10-02T08:51:19Z",
              "label": {
                "id": "LA_kwDOFcwZ1c8AAAABAt13Ow",
                "name": "delegated"
              }
            },
            {
              "__typename": "UnlabeledEvent",
              "id": "UNLE_lADOFcwZ1c5vXZ0ozwAAAAJzQLUn",
              "createdAt": "2023-10-02T08:51:20Z",
              "label": {
                "id": "LA_kwDOFcwZ1c7ECuhA",
                "name": "awaiting-review"
              }
            },
            {
              "__typename": "PullRequestCommit",
              "commit": {
                "oid": "cae2c37f1cd72ed23f5291ca970e033e8b60c4f6"
              }
            },
            {
              "__typename": "PullRequestCommit",
              "commit": {
                "oid": "5c27edfe8ae99b200c16b8d9bb049a57ccc5448b"
              }
            },
            {
              "__typename": "PullRequestCommit",
              "commit": {
                "oid": "5a767eae921bbdbeb8df0488a1fcfd4347167ebc"
              }
            },
            {
              "__typename": "PullRequestCommit",
              "commit": {
                "oid": "0c9add7a780c4aac2dbe7b6376dc44448ef5779d"
              }
            },
            {
              "__typename": "IssueComment",
              "id": "IC_kwDOFcwZ1c5pEC8P",
              "createdAt": "2023-10-14T06:47:35Z",
              "body": "bors merge",
              "author": {
                "login": "Parcly-Taxel"
              }
            },
            {
              "__typename": "ReferencedEvent"
            },
            {
              "__typename": "PullRequestCommit",
              "commit": {
                "oid": "e09355f8dc198cf9231458bcb5dde129a36aadbc"
              }
            },
            {
              "__typename": "IssueComment",
              "id": "IC_kwDOFcwZ1c5pEDK5",
              "createdAt": "2023-10-14T06:52:10Z",
              "body": "Canceled.",
              "author": {
                "login": "bors"
              }
            },
            {
              "__typename": "PullRequestCommit",
              "commit": {
                "oid": "fb09cf6820561d51553c7ca5de6129be554265c5"
              }
            },
            {
              "__typename": "IssueComment",
              "id": "IC_kwDOFcwZ1c5pED3L",
              "createdAt": "2023-10-14T07:05:23Z",
              "body": "bors merge",
              "author": {
                "login": "Parcly-Taxel"
              }
            },
            {
              "__typename": "ReferencedEvent"
            },
            {
              "__typename": "IssueComment",
              "id": "IC_kwDOFcwZ1c5pELSa",
              "createdAt": "2023-10-14T07:39:42Z",
              "body": "Pull request successfully merged into master.\n\n  Build succeeded!\n\n  The publicly hosted instance of bors-ng is deprecated and will go away soon.\n\n  If you want to self-host your own instance, [instructions are here][instructions].\n  For more help, visit [the forum].\n\n  If you want to switch to GitHub's built-in merge queue, visit [their help page][gh].\n\n  [instructions]: https://github.com/bors-ng/bors-ng#how-to-set-up-your-own-real-instance\n  [the forum]: https://forum.bors.tech\n  [gh]: https://docs.github.com/en/repositories/configuring-branches-and-merges-in-your-repository/configuring-pull-request-merges/managing-a-merge-queue\n\n\n\n  * [Build](https://github.com/leanprover-community/mathlib4/actions/runs/6516233908/job/17699534268)\n  * [Check all files imported](https://github.com/leanprover-community/mathlib4/actions/runs/6516233908/job/17699534339)\n  * [Lint style](https://github.com/leanprover-community/mathlib4/actions/runs/6516233908/job/17699534496)",
              "author": {
                "login": "bors"
              }
            },
            {
              "__typename": "RenamedTitleEvent"
            },
            {
              "__typename": "ClosedEvent",
              "id": "CE_lADOFcwZ1c5vXZ0ozwAAAAJ66b4e",
              "createdAt": "2023-10-14T07:39:44Z"
            },
            {
              "__typename": "HeadRefDeletedEvent",
              "id": "HRDE_lADOFcwZ1c5vXZ0ozwAAAAJ66b8A",
              "createdAt": "2023-10-14T07:39:47Z"
            }
          ]
        }
      }
    }
  }
}
